mindmaster/__init__.py
mindmaster-0.0.1.dist-info/LICENSE
mindmaster-0.0.1.dist-info/METADATA
mindmaster-0.0.1.dist-info/WHEEL
mindmaster-0.0.1.dist-info/top_level.txt
mindmaster-0.0.1.dist-info/RECORD
