Metadata-Version: 2.2
Name: mindmaster
Version: 0.0.1
Summary: MindMaster is a library that includes many models of CTR Prediction & Recommender System by MindSpore.
Home-page: https://github.com/uliontse/mindmaster
Author: UlionTse
Author-email: uliontse@outlook.com
License: Apache-2.0
Project-URL: Source, https://github.com/UlionTse/mindmaster
Project-URL: Changelog, https://github.com/UlionTse/mindmaster/blob/main/change_log.txt
Project-URL: Documentation, https://github.com/UlionTse/mindmaster/blob/main/README.md
Keywords: Machine Learning,Deep Learning,CTR Prediction,Recommender System
Classifier: Development Status :: 1 - Planning
Classifier: Intended Audience :: Developers
Classifier: License :: OSI Approved :: Apache Software License
Classifier: Programming Language :: Python :: 3 :: Only
Classifier: Programming Language :: Python :: 3.9
Classifier: Programming Language :: Python :: 3.10
Classifier: Programming Language :: Python :: 3.11
Classifier: Programming Language :: Python :: 3.12
Classifier: Topic :: Scientific/Engineering
Classifier: Topic :: Scientific/Engineering :: Artificial Intelligence
Classifier: Topic :: Software Development
Classifier: Topic :: Software Development :: Libraries
Classifier: Topic :: Software Development :: Libraries :: Python Modules
Requires-Python: >=3.9
License-File: LICENSE
Requires-Dist: numpy>=1.26.4
Requires-Dist: mindspore>=2.4.10
Provides-Extra: pypi
Requires-Dist: build>=1.2.2; extra == "pypi"
Requires-Dist: twine>=6.0.1; extra == "pypi"
Dynamic: author
Dynamic: author-email
Dynamic: classifier
Dynamic: description
Dynamic: description-content-type
Dynamic: home-page
Dynamic: keywords
Dynamic: license
Dynamic: project-url
Dynamic: provides-extra
Dynamic: requires-dist
Dynamic: requires-python
Dynamic: summary
